KityEngine/__init__.py
KityEngine/app.py
KityEngine/builder.py
KityEngine/graphics/__init__.py
KityEngine/graphics/image.py
KityEngine/graphics/label.py
Kity-0.0.0.dist-info/METADATA
Kity-0.0.0.dist-info/WHEEL
Kity-0.0.0.dist-info/top_level.txt
Kity-0.0.0.dist-info/RECORD
