Metadata-Version: 2.1
Name: Kity
Version: 0.0.0
Summary: A simple graphics module.
Home-page: UNKNOWN
Author: Hrishikesh Arun
Author-email: hrishikesh28arun@gmail.com
License: UNKNOWN
Platform: UNKNOWN
Classifier: Topic :: Education
Classifier: License :: OSI Approved :: MIT License
Classifier: Operating System :: Microsoft :: Windows :: Windows 10
Classifier: Intended Audience :: Education
Classifier: Programming Language :: Python :: 3
Classifier: Development Status :: 4 - Beta
Requires-Python: >=3.8
Requires-Dist: Kivy[full]
Requires-Dist: Kivy (>=2.0.0)
Requires-Dist: kivy-examples
